archon/completions/__init__.py
archon/completions/archon.py
archon/completions/components/Component.py
archon/completions/components/Critic.py
archon/completions/components/Fuser.py
archon/completions/components/Generator.py
archon/completions/components/Ranker.py
archon/completions/components/Unit_Test_Evaluator.py
archon/completions/components/Unit_Test_Generator.py
archon/completions/components/Verifier.py
archon/completions/components/__init__.py
archon/completions/components/prompts.py
archon/completions/utils.py
archon_ai-0.1.4.dist-info/METADATA
archon_ai-0.1.4.dist-info/WHEEL
archon_ai-0.1.4.dist-info/RECORD
